[
	{
		"PluginName": "OpenCVCamera",
		"InputType": "NoInput",
		"PluginID": "0",
		"Inputs": "NoInput",
		"Outputs": "ImageQueue",
		"Visualize": "True"
	},
	{
		"PluginName": "HSVTransform",
		"InputType": "ImageQueue",
		"PluginID": "1",
		"Inputs": "0",
		"Outputs": "ImageQueue",
		"Visualize": "False"
	},
	{
		"PluginName": "GoogleCloudAnnotator",
		"InputType": "ImageQueueDISABLE",
		"PluginID": "0",
		"Inputs": "0",
		"Outputs": "Labels",
		"Visualize": "False"
	},
	{
		"PluginName": "MobileNetSSD",
		"InputType": "ImageQueue",
		"PluginID": "2",
		"Inputs": "0",
		"Outputs": "ImageQueue",
		"Visualize": "False"
	},
	{
		"PluginName": "ZedPositioning",
		"InputType": "None",
		"PluginID": "0",
		"Inputs": "NoInput",
		"Outputs": "PositionQueue",
		"Visualize": "True"
	}
]
		
